pymagic9/__init__.py
pymagic9/py.typed
pymagic9/pymagic9.py
pymagic9/pymagic9.pyi
pymagic9-0.9.0.dist-info/LICENSE
pymagic9-0.9.0.dist-info/METADATA
pymagic9-0.9.0.dist-info/WHEEL
pymagic9-0.9.0.dist-info/top_level.txt
pymagic9-0.9.0.dist-info/RECORD
