Metadata-Version: 2.1
Name: pymagic9
Version: 0.9.0
Summary: This is a Python library based on calling of frame's stack at runtime and mainly implements some C# features.
Home-page: https://github.com/sammnnz/pymagic9
Author: Sam Nazarov
Author-email: samnnazarov@gmail.com
License: Apache License 2.0
Project-URL: Bug Tracker, https://github.com/sammnnz/pymagic9/issues
Project-URL: Changelog, https://github.com/sammnnz/pymagic9/blob/master/CHANGELOG.md
Project-URL: Source code, https://github.com/sammnnz/pymagic9
Keywords: C#,frame,getframe,isfunctionincallchain,nameof,stackframe
Platform: any
Classifier: Development Status :: 5 - Production/Stable
Classifier: Intended Audience :: Developers
Classifier: License :: OSI Approved :: Apache Software License
Classifier: Operating System :: OS Independent
Classifier: Programming Language :: Python
Classifier: Programming Language :: Python :: 2.7
Classifier: Programming Language :: Python :: 3.6
Classifier: Programming Language :: Python :: 3.7
Classifier: Programming Language :: Python :: 3.8
Classifier: Programming Language :: Python :: 3.9
Classifier: Programming Language :: Python :: 3.10
Classifier: Programming Language :: Python :: Implementation :: CPython
Classifier: Topic :: Software Development :: Libraries :: Python Modules
Requires-Python: !=3.0.*,!=3.1.*,!=3.2.*,!=3.3.*,!=3.4.*,!=3.5.*,<3.11,>=2.7
License-File: LICENSE
Requires-Dist: multipledispatch ==0.6.0
Provides-Extra: testing
Requires-Dist: six ==1.13.0 ; extra == 'testing'
Requires-Dist: pytest ==4.6.11 ; extra == 'testing'
Requires-Dist: pytest-cov ==2.8.1 ; extra == 'testing'
Requires-Dist: coverage ==5.2.1 ; extra == 'testing'
Requires-Dist: codecov ==2.1.13 ; extra == 'testing'
Requires-Dist: pipenv ==2023.7.11 ; extra == 'testing'
Requires-Dist: tox <4.0.0,>=3.24.3 ; extra == 'testing'
Requires-Dist: mypy ==0.910 ; extra == 'testing'
Requires-Dist: flake8 ==3.9.2 ; extra == 'testing'
Requires-Dist: importlib-metadata <5,>=4.13.0 ; extra == 'testing'
Requires-Dist: pre-commit ==2.21.0 ; extra == 'testing'
